odoo/addons/repair_calendar_view/README.rst
odoo/addons/repair_calendar_view/__init__.py
odoo/addons/repair_calendar_view/__manifest__.py
odoo/addons/repair_calendar_view/i18n/es.po
odoo/addons/repair_calendar_view/i18n/it.po
odoo/addons/repair_calendar_view/i18n/repair_calendar_view.pot
odoo/addons/repair_calendar_view/models/__init__.py
odoo/addons/repair_calendar_view/models/repair.py
odoo/addons/repair_calendar_view/readme/CONTRIBUTORS.rst
odoo/addons/repair_calendar_view/readme/DESCRIPTION.rst
odoo/addons/repair_calendar_view/readme/USAGE.rst
odoo/addons/repair_calendar_view/static/description/icon.png
odoo/addons/repair_calendar_view/static/description/index.html
odoo/addons/repair_calendar_view/tests/__init__.py
odoo/addons/repair_calendar_view/tests/test_repair_calendar_view.py
odoo/addons/repair_calendar_view/views/mrp_repair_view.xml
odoo_addon_repair_calendar_view-16.0.1.0.0.6.dist-info/METADATA
odoo_addon_repair_calendar_view-16.0.1.0.0.6.dist-info/WHEEL
odoo_addon_repair_calendar_view-16.0.1.0.0.6.dist-info/top_level.txt
odoo_addon_repair_calendar_view-16.0.1.0.0.6.dist-info/RECORD
